MANIFEST.in
README.md
setup.cfg
setup.py
TemplateCreator/__init__.py
TemplateCreator/__main__.py
TemplateCreator/template_creator.py
TemplateCreator/template_options.py
TemplateCreator.egg-info/PKG-INFO
TemplateCreator.egg-info/SOURCES.txt
TemplateCreator.egg-info/dependency_links.txt
TemplateCreator.egg-info/requires.txt
TemplateCreator.egg-info/top_level.txt
TemplateCreator/templates/actions.js
TemplateCreator/templates/class-component.jsx
TemplateCreator/templates/css-module.scss
TemplateCreator/templates/function-component.jsx
TemplateCreator/templates/readme.md
TemplateCreator/templates/reducer.js
TemplateCreator/templates/service.js
TemplateCreator/templates/state.js
TemplateCreator/templates/styles.js
TemplateCreator/templates/test.jsx
TemplateCreator/templates/ts-actions.ts
TemplateCreator/templates/ts-connected-component.tsx
TemplateCreator/templates/ts-function-component.tsx
TemplateCreator/templates/ts-reducer.ts
TemplateCreator/templates/ts-state.ts
TemplateCreator/templates/ts-styles.ts