Metadata-Version: 1.1
Name: TemplateCreator
Version: 0.45
Summary: This project is intended unify boilerplate code between team members and make the setup process for starting a new component shorted and less tedious.
Home-page: https://github.com/galbh/template-generator
Author: Gal Ben Haim
Author-email: gal_ben_haim@yahoo.com
License: MIT
Download-URL: https://github.com/galbh/template-generator/archive/v_40.tar.gz
Keywords: TEMPLATE
Platform: UNKNOWN
Classifier: Development Status :: 3 - Alpha
Classifier: Intended Audience :: Developers
Classifier: Topic :: Software Development :: Build Tools
Classifier: License :: OSI Approved :: MIT License
Classifier: Programming Language :: Python :: 3
